ancient_helper_kit/__init__.py
ancient_helper_kit/bam_handling/__init__.py
ancient_helper_kit/bam_handling/summarize_bam_file_in_csv.py
ancient_helper_kit/kraken2/__init__.py
ancient_helper_kit/kraken2/compute_confidence_score.py
ancient_helper_kit/kraken2/create_viral_dna_fasta.py
ancient_helper_kit/util/__init__.py
ancient_helper_kit/util/general.py
ancient_helper_kit-0.0.7.dist-info/LICENSE
ancient_helper_kit-0.0.7.dist-info/METADATA
ancient_helper_kit-0.0.7.dist-info/WHEEL
ancient_helper_kit-0.0.7.dist-info/top_level.txt
ancient_helper_kit-0.0.7.dist-info/RECORD
