Metadata-Version: 2.1
Name: ancient-helper-kit
Version: 0.0.7
Summary: helper functions to be used in a pipeline for virus discovery
Home-page: https://github.com/UdoGi/ancient_helper_kit
Author: Udo Gieraths
Author-email: udo.gieraths@charite.de
License: UNKNOWN
Platform: UNKNOWN
Classifier: Programming Language :: Python :: 3
Classifier: License :: OSI Approved :: MIT License
Classifier: Operating System :: OS Independent
Requires-Python: >=3.8
License-File: LICENSE
Requires-Dist: biopython
